Metadata-Version: 2.1
Name: flamel
Version: 0.2.1
Summary: Flips yaml input to json and vice versa
Home-page: https://github.com/SpamapS/flamel
Author: Clint Byrum
Author-email: clint@fewbar.com
License: UNKNOWN
Platform: UNKNOWN
Classifier: Intended Audience :: Information Technology
Classifier: Intended Audience :: Developers
Classifier: License :: OSI Approved :: Apache Software License
Classifier: Operating System :: POSIX :: Linux
Classifier: Programming Language :: Python
Classifier: Programming Language :: Python :: 2
Classifier: Programming Language :: Python :: 2.7
Classifier: Programming Language :: Python :: 2.6
Classifier: Programming Language :: Python :: 3
